setup.py
Demo8799/__init__.py
Demo8799/demo1.py
Demo8799/demo2.py
Demo8799.egg-info/PKG-INFO
Demo8799.egg-info/SOURCES.txt
Demo8799.egg-info/dependency_links.txt
Demo8799.egg-info/top_level.txt