Metadata-Version: 2.1
Name: Demo8799
Version: 1.0
Summary: 测试本地发布模块
Author: dgw
Author-email: 879967992@qq.com
